cookie_test/__init__.py
cookie_test/__main__.py
cookie_test/py.typed
cookie_test-0.0.0.dist-info/entry_points.txt
cookie_test-0.0.0.dist-info/LICENSE
cookie_test-0.0.0.dist-info/WHEEL
cookie_test-0.0.0.dist-info/METADATA
cookie_test-0.0.0.dist-info/RECORD
