Metadata-Version: 2.1
Name: cookie-test
Version: 0.0.0
Summary: Cookie Test
Home-page: https://github.com/soshi117/cookie-test
License: MIT
Author: Soshi Mizutani
Author-email: soshi.mizutani@oist.jp
Requires-Python: >=3.7,<4.0
Classifier: Development Status :: 1 - Planning
Classifier: License :: OSI Approved :: MIT License
Classifier: Programming Language :: Python :: 3
Classifier: Programming Language :: Python :: 3.7
Classifier: Programming Language :: Python :: 3.8
Classifier: Programming Language :: Python :: 3.9
Classifier: Programming Language :: Python :: 3.10
Classifier: Programming Language :: Python :: 3.11
Requires-Dist: click (>=8.0.1)
Project-URL: Changelog, https://github.com/soshi117/cookie-test/releases
Project-URL: Documentation, https://cookie-test.readthedocs.io
Project-URL: Repository, https://github.com/soshi117/cookie-test
